covpred.cpython-39-aarch64-linux-gnu.so
covpred-1.0.4.dist-info/LICENSE
covpred-1.0.4.dist-info/RECORD
covpred-1.0.4.dist-info/WHEEL
covpred-1.0.4.dist-info/METADATA
covpred-1.0.4.dist-info/top_level.txt
