Metadata-Version: 2.1
Name: covpred
Version: 1.0.4
Summary: A library containing algorithms to model population dynamics resulting from infectious diseases and more.
Home-page: UNKNOWN
Author: Devansh Rastogi, HeinzHermann, RefreshingAutomate
Author-email: hello@covpred.de
License: UNKNOWN
Platform: UNKNOWN
Requires-Python: >=3.6
Provides-Extra: test
Requires-Dist: pytest (>=6.0) ; extra == 'test'
